minecraftschematics/__init__.py
minecraftschematics/schematic.py
minecraftschematics/utils.py
minecraftschematics-0.1.2.dist-info/METADATA
minecraftschematics-0.1.2.dist-info/WHEEL
minecraftschematics-0.1.2.dist-info/top_level.txt
minecraftschematics-0.1.2.dist-info/RECORD
