Metadata-Version: 2.1
Name: minecraftschematics
Version: 0.1.2
Summary: A library for working with Minecraft Schematics in Python with numpy
Author: Gabriel Werneck Paiva
Author-email: gwerneckpaiva@gmail.com
License: MIT
Keywords: python,minecraft,schematic,numpy,nbtlib
Requires-Dist: numpy
Requires-Dist: nbtlib
